sphinx_simplepdf/__init__.py
sphinx_simplepdf/builders/__init__.py
sphinx_simplepdf/builders/debug.py
sphinx_simplepdf/builders/simplepdf.py
sphinx_simplepdf/directives/__init__.py
sphinx_simplepdf/directives/ifbuilder.py
sphinx_simplepdf/directives/ifinclude.py
sphinx_simplepdf/directives/pdfinclude.py
sphinx_simplepdf/themes/simplepdf_theme/__init__.py
sphinx_simplepdf/themes/simplepdf_theme/back_cover.html
sphinx_simplepdf/themes/simplepdf_theme/cover.html
sphinx_simplepdf/themes/simplepdf_theme/debug.html
sphinx_simplepdf/themes/simplepdf_theme/layout.html
sphinx_simplepdf/themes/simplepdf_theme/page.html
sphinx_simplepdf/themes/simplepdf_theme/theme.conf
sphinx_simplepdf/themes/simplepdf_theme/static/fonts/FiraMono-Bold.ttf
sphinx_simplepdf/themes/simplepdf_theme/static/fonts/FiraMono-Medium.ttf
sphinx_simplepdf/themes/simplepdf_theme/static/fonts/FiraMono-Regular.ttf
sphinx_simplepdf/themes/simplepdf_theme/static/fonts/FiraSans-Bold.otf
sphinx_simplepdf/themes/simplepdf_theme/static/fonts/FiraSans-Italic.otf
sphinx_simplepdf/themes/simplepdf_theme/static/fonts/FiraSans-Light.otf
sphinx_simplepdf/themes/simplepdf_theme/static/fonts/FiraSans-LightItalic.otf
sphinx_simplepdf/themes/simplepdf_theme/static/fonts/FiraSans-Regular.otf
sphinx_simplepdf/themes/simplepdf_theme/static/fonts/WorkSans-Bold.ttf
sphinx_simplepdf/themes/simplepdf_theme/static/fonts/WorkSans-Regular.ttf
sphinx_simplepdf/themes/simplepdf_theme/static/fonts/WorkSans-SemiBold.ttf
sphinx_simplepdf/themes/simplepdf_theme/static/fonts/fa-solid-900.eot
sphinx_simplepdf/themes/simplepdf_theme/static/fonts/fa-solid-900.svg
sphinx_simplepdf/themes/simplepdf_theme/static/fonts/fa-solid-900.ttf
sphinx_simplepdf/themes/simplepdf_theme/static/fonts/fa-solid-900.woff
sphinx_simplepdf/themes/simplepdf_theme/static/fonts/fa-solid-900.woff2
sphinx_simplepdf/themes/simplepdf_theme/static/styles/sources/_admonition.scss
sphinx_simplepdf/themes/simplepdf_theme/static/styles/sources/_alerts.scss
sphinx_simplepdf-1.6.0.dist-info/AUTHORS.rst
sphinx_simplepdf-1.6.0.dist-info/LICENSE
sphinx_simplepdf-1.6.0.dist-info/METADATA
sphinx_simplepdf-1.6.0.dist-info/WHEEL
sphinx_simplepdf-1.6.0.dist-info/entry_points.txt
sphinx_simplepdf-1.6.0.dist-info/top_level.txt
sphinx_simplepdf-1.6.0.dist-info/RECORD
