Metadata-Version: 2.1
Name: sphinx-simplepdf
Version: 1.6.0
Summary: An easy to use PDF Builder for Sphinx with a modern PDF-Theme.
Home-page: https://sphinx-simplepdf.readthedocs.io
Download-URL: https://github.com/useblocks/sphinx-simplepdf
Author: team useblocks
Author-email: info@useblocks.com
License: MIT
Classifier: Framework :: Sphinx
Classifier: Framework :: Sphinx :: Theme
Classifier: Development Status :: 5 - Production/Stable
Classifier: License :: OSI Approved :: MIT License
Classifier: Intended Audience :: Developers
Classifier: Programming Language :: Python :: 3
Classifier: Operating System :: OS Independent
Classifier: Topic :: Documentation
Classifier: Topic :: Software Development :: Documentation
License-File: LICENSE
License-File: AUTHORS.rst
